setup.py
winCurses/WDisp.py
winCurses/WInput.py
winCurses/WList.py
winCurses/WNotif.py
winCurses/WProgress.py
winCurses/WTitle.py
winCurses/Win.py
winCurses/__init__.py
winCurses/test.py
winCurses.egg-info/PKG-INFO
winCurses.egg-info/SOURCES.txt
winCurses.egg-info/dependency_links.txt
winCurses.egg-info/not-zip-safe
winCurses.egg-info/top_level.txt