Metadata-Version: 1.0
Name: winCurses
Version: 0.2.0.post5
Summary: A curses wrapper to draw some HTML-like windows
Home-page: http://git.beerstorm.info/Beerstorm/winCurses
Author: Beerstorm
Author-email: beerstorm.emberbeard@gmail.com
License: GPLv3
Platform: UNKNOWN
